pysubgroup/__init__.py
pysubgroup/algorithms.py
pysubgroup/binary_target.py
pysubgroup/constraints.py
pysubgroup/datasets.py
pysubgroup/fi_target.py
pysubgroup/gp_growth.py
pysubgroup/measures.py
pysubgroup/model_target.py
pysubgroup/numeric_target.py
pysubgroup/refinement_operator.py
pysubgroup/representations.py
pysubgroup/subgroup_description.py
pysubgroup/utils.py
pysubgroup/visualization.py
pysubgroup/data/credit-g.arff
pysubgroup/data/titanic.csv
pysubgroup-0.8.0.dist-info/LICENSE.txt
pysubgroup-0.8.0.dist-info/METADATA
pysubgroup-0.8.0.dist-info/WHEEL
pysubgroup-0.8.0.dist-info/top_level.txt
pysubgroup-0.8.0.dist-info/RECORD
