Metadata-Version: 2.1
Name: pysubgroup
Version: 0.8.0
Summary: pysubgroup is a Python library for the data analysis task of subgroup discovery.
Home-page: https://github.com/flemmerich/pysubgroup
Author: Florian Lemmerich, Felix Stamm, Martin Becker
Author-email: florian@lemmerich.net
License: Apache 2.0
Project-URL: Documentation, https://pysubgroup.readthedocs.io/
Project-URL: Source, https://github.com/flemmerich/pysubgroup
Project-URL: Tracker, https://github.com/flemmerich/pysubgroup/issues
Project-URL: Download, https://pypi.org/project/pysubgroup/#files
Platform: any
Classifier: Development Status :: 4 - Beta
Classifier: Intended Audience :: Science/Research
Classifier: Intended Audience :: Developers
Classifier: Programming Language :: Python
Classifier: Topic :: Software Development
Classifier: Topic :: Scientific/Engineering
Classifier: Operating System :: Microsoft :: Windows
Classifier: Operating System :: POSIX
Classifier: Operating System :: Unix
Classifier: Operating System :: MacOS
Classifier: Programming Language :: Python :: 3
Classifier: Programming Language :: Python :: 3.5
Classifier: Programming Language :: Python :: 3.6
Classifier: Programming Language :: Python :: 3.7
Classifier: Programming Language :: Python :: Implementation :: CPython
Requires-Python: >=3.6
License-File: LICENSE.txt
Requires-Dist: pandas >=0.24.0
Requires-Dist: scipy
Requires-Dist: numpy
Requires-Dist: matplotlib
Requires-Dist: importlib-metadata ; python_version < "3.8"
Provides-Extra: testing
Requires-Dist: setuptools ; extra == 'testing'
Requires-Dist: pytest ; extra == 'testing'
Requires-Dist: pytest-cov ; extra == 'testing'
